__init__.py
example_madhav/__init__.py
example_madhav/calculator/add.py
example_madhav/calculator/sub.py
thisismadhav-0.1.0.dist-info/METADATA
thisismadhav-0.1.0.dist-info/WHEEL
thisismadhav-0.1.0.dist-info/top_level.txt
thisismadhav-0.1.0.dist-info/RECORD
