Metadata-Version: 2.4
Name: thisismadhav
Version: 0.1.0
Summary: Add your description here
Requires-Python: >=3.12
Requires-Dist: pandas>=2.3.3
